lazyscribe_yaml/__init__.py
lazyscribe_yaml/_meta.py
lazyscribe_yaml-0.1.3.dist-info/WHEEL
lazyscribe_yaml-0.1.3.dist-info/entry_points.txt
lazyscribe_yaml-0.1.3.dist-info/METADATA
lazyscribe_yaml-0.1.3.dist-info/RECORD
